odoo8_addon_base_bank_account_number_unique-8.0.1.1.0.99.dev4-py3.8-nspkg.pth
odoo_addons/base_bank_account_number_unique/README.rst
odoo_addons/base_bank_account_number_unique/__init__.py
odoo_addons/base_bank_account_number_unique/__openerp__.py
odoo_addons/base_bank_account_number_unique/i18n/base_bank_account_number_unique.pot
odoo_addons/base_bank_account_number_unique/i18n/de.po
odoo_addons/base_bank_account_number_unique/i18n/es.po
odoo_addons/base_bank_account_number_unique/i18n/fi.po
odoo_addons/base_bank_account_number_unique/i18n/fr.po
odoo_addons/base_bank_account_number_unique/i18n/lt_LT.po
odoo_addons/base_bank_account_number_unique/i18n/nl.po
odoo_addons/base_bank_account_number_unique/i18n/pt_BR.po
odoo_addons/base_bank_account_number_unique/i18n/pt_PT.po
odoo_addons/base_bank_account_number_unique/i18n/sl.po
odoo_addons/base_bank_account_number_unique/models/__init__.py
odoo_addons/base_bank_account_number_unique/models/res_partner_bank.py
odoo_addons/base_bank_account_number_unique/static/description/icon.png
odoo_addons/base_bank_account_number_unique/tests/__init__.py
odoo_addons/base_bank_account_number_unique/tests/test_base_bank_account_number_unique.py
odoo8_addon_base_bank_account_number_unique-8.0.1.1.0.99.dev4.dist-info/METADATA
odoo8_addon_base_bank_account_number_unique-8.0.1.1.0.99.dev4.dist-info/WHEEL
odoo8_addon_base_bank_account_number_unique-8.0.1.1.0.99.dev4.dist-info/namespace_packages.txt
odoo8_addon_base_bank_account_number_unique-8.0.1.1.0.99.dev4.dist-info/top_level.txt
odoo8_addon_base_bank_account_number_unique-8.0.1.1.0.99.dev4.dist-info/RECORD
